ascii_magic/__init__.py
ascii_magic/ascii_art.py
ascii_magic/ascii_art_font.py
ascii_magic/constants.py
ascii_magic/functions.py
ascii_magic/fonts/courier_prime.ttf
ascii_magic/tests/__init__.py
ascii_magic/tests/chicken_transparent.png
ascii_magic/tests/lion.jpg
ascii_magic/tests/test_chars_by_density.py
ascii_magic/tests/test_enhance.py
ascii_magic/tests/test_exposed_pil_image.py
ascii_magic/tests/test_from_clipboard.py
ascii_magic/tests/test_from_file.py
ascii_magic/tests/test_from_gemini.py
ascii_magic/tests/test_from_image_object.py
ascii_magic/tests/test_from_swarmui.py
ascii_magic/tests/test_from_url.py
ascii_magic/tests/test_palette.py
ascii_magic/tests/test_quick_test.py
ascii_magic/tests/test_to_file.py
ascii_magic/tests/test_to_html_file.py
ascii_magic/tests/test_to_image_file.py
ascii_magic/tests/test_to_terminal.py
ascii_magic-2.7.2.data/data/ascii_magic/fonts/courier_prime.ttf
ascii_magic-2.7.2.data/data/ascii_magic/tests/chicken_transparent.png
ascii_magic-2.7.2.data/data/ascii_magic/tests/lion.jpg
ascii_magic-2.7.2.dist-info/LICENCE
ascii_magic-2.7.2.dist-info/METADATA
ascii_magic-2.7.2.dist-info/WHEEL
ascii_magic-2.7.2.dist-info/top_level.txt
ascii_magic-2.7.2.dist-info/RECORD
