Metadata-Version: 2.1
Name: ascii_magic
Version: 2.7.2
Summary: Converts pictures into ASCII art
Home-page: https://github.com/LeandroBarone/python-ascii_magic
Author: Leandro Barone
Author-email: web@leandrobarone.com.ar
Classifier: Programming Language :: Python :: 3
Classifier: License :: OSI Approved :: MIT License
Classifier: Operating System :: OS Independent
Requires-Python: >=3.5
License-File: LICENCE
Requires-Dist: Pillow
